Project1/src/verilog/rtl/psdsqrt.v

module psdsqrt
	#(parameter NBITSIN = 16)
	( 				 
				 input clock, // master clock rising edge 
				 input reset, // synch reset active high 
				 input start, // start a new square root, one clock pulse 
				 input stop, // load output register, one clock pulse 
				 input [NBITSIN-1:0] xin, // operand, unsigned integer 32 bits 
				 output reg [NBITSIN/2-1:0] sqrt // sqrt( xin ), unsigned integer 16 bits 
			  );
wire [NBITSIN+7:0] inteiro;			  
reg [NBITSIN/2+3:0] tempsqrt;
wire [NBITSIN/2+3:0] testsqrt;
wire [NBITSIN+7:0] sqtestsqrt;			  
wire greater;
reg [NBITSIN+7:0] A_value;
reg [NBITSIN/2+3:0] other;
wire [3:0]frac;
wire [NBITSIN/2-1:0] pint;

assign inteiro = xin<<8;

always @(posedge clock)
begin
if ( start)
A_value <= inteiro;
end

assign sqtestsqrt= (testsqrt * testsqrt);
assign greater=(A_value >= sqtestsqrt);

// assign tempsqrt=(start)?16'h0000:
				// (greater)?testsqrt:
				// tempsqrt;
				
always @(posedge clock)
begin
if ( start )
tempsqrt <= {(NBITSIN/2+4){1'b0}};
else if (greater)
tempsqrt<= testsqrt;
else
tempsqrt<=tempsqrt;
end
// assign other=(start)? 16'h8000:(other>>1);

always @(posedge clock)
begin
if ( start )
other <= {1'b1, {(NBITSIN/2+3){1'b0}}};
else
other<=(other>>1);
end

assign frac=tempsqrt[3:0];
assign pint=tempsqrt[NBITSIN/2+3:4];

always @(posedge clock)
begin
if ( stop) begin
if(frac < 8) 
	sqrt<= pint;
	else if(frac == 8) 
	sqrt<= (pint+ pint[0]);
	else if (frac >= 9) 
	sqrt<= (pint+1);

end
end
			  
assign testsqrt= (tempsqrt | other);

always @(posedge clock)
begin
if (reset)
	A_value={(NBITSIN+8){1'b0}};
	
end

endmodule

Project1/src/verilog/rtl/sec_controller.v
module sec_controller
		#(parameter NBITSIN = 16)
				( input run,
				 input clock, // master clock rising edge 
				 input reset,
				 output reg busy,
				 output reg start,
				 output reg stop
						);
reg [1:0]state;
reg[3:0] conta;	

always @(posedge clock )
begin
 start<= run & !busy;
end
always @(posedge clock )
  begin 
	  if (reset) begin
	  state<= 2'b00;
	  conta<=0;
	  busy<=0;
	  stop<=0;
	 end
	  else begin
	  
	  case (state)
	  2'b00: begin if (run) begin
				busy<=1;
				state<=2'b01;
				conta<=4'b0000;
							end
				else begin
				state<=2'b00;
				conta<=4'b0000;	
					end
			end
	 2'b01: begin if(run==0)begin			  
			   conta<=conta + 1;
			   state<=2'b10;
							end
			   else
				   state<=2'b01;
			end
			
	 2'b10: begin if(conta == (NBITSIN/2+4)) begin
			   stop <= 1'b1;
			   state <= 2'b11;				
				end
			   else begin
			   conta<=conta + 1;			    
			   state<=2'b10;
					end
			end
			
	 2'b11: begin
			   stop <= 1'b0;
			   busy <= 1'b0;
			   state <= 2'b00;	
			   //$display("%d", conta);			   
			   conta<=0;
			end
	 default: state<= 2'b00;
			endcase
			end
  end
	

					
endmodule

Project1/src/verilog/testbench/sec_controller_tb.v
/* 
PSD 2021-2022

Lab 1 - Design and verification of a sequential square root calculator

	This Verilog code is property of University of Porto
	Its utilization beyond the scope of the course Digital Systems Design
	(Projeto de Sistemas Digitais) of the Master in Electrical 
	and Computer Engineering requires explicit authorization from the author.
	
	jca@fe.up.pt, April 2022
	
*/

`timescale 1ns / 100ps

module sec_controller_tb;
 
// general parameters 
parameter CLOCK_PERIOD = 10;              // Clock period in ns
parameter MAX_SIM_TIME = 100_000_000;     // Set the maximum simulation time (time units=ns)
parameter NBITS=16;// par
// Registers for driving the inputs:

reg  clock, reset, run; 
wire start, stop, busy;

reg  [NBITS-1:0] x;
wire [NBITS/2-1:0] sqrt;
// Instantiate the module under verification:


sec_controller  #(.NBITSIN(NBITS)) sec_1    
		( 		.run(run),
				.clock(clock), // master clock rising edge 
				.reset(reset),
				.busy(busy),
				.start(start),
				.stop(stop)
						);
psdsqrt #(.NBITSIN(NBITS)) psdsqrt_2
      ( 	
	    .clock(clock), // master clock, active in the positive edge
        .reset(reset), // master reset, synchronous and active high
		
        .start(start), // set to 1 during one clock cycle to start a sqrt
        .stop(stop),   // set to 1 during one clock cycle to load the output registers
		
        .xin(x),       // the operands
        .sqrt(sqrt)
        );    						

// Setup initial signals
initial
begin
$dumpfile("sec_controller_tb.vcd"); 
$dumpvars(0, sec_controller_tb);
  x=0;
  run=0;
  clock = 0;
  reset = 0;
 // defparam psdsqrt_1.NBITSIN= NBITS;
end

//---------------------------------------------------
// generate a 50% duty-cycle clock signal
initial
begin  
  forever
    # (CLOCK_PERIOD / 2 ) clock = ~clock;
end

//---------------------------------------------------
// Apply the initial reset for 2 clock cycles:
initial
begin
  # (CLOCK_PERIOD/3) // wait a fraction of the clock period to 
                     // misalign the reset pulse with the clock edges:
  reset = 1;
  # (2 * CLOCK_PERIOD ) // apply the reset for 2 clock periods
  reset = 0;
  
end

//---------------------------------------------------
// Set the maximum simulation time:
initial
begin
  # ( MAX_SIM_TIME )
  $stop;
end

//---------------------------------------------------
// The verification program (THIS IS TRUE A PROGRAM!)
initial
begin
  // Wait 10 clock periods
  #( 10*CLOCK_PERIOD );

  //startstates(1);
  startstates(100);
  $display("%d", sqrt);
  startstates(12);
  $display("%d", sqrt);
  startstates(13);
  $display("%d", sqrt);
  startstates(1057);
  $display("%d", sqrt);
  startstates(4300);
  $display("%d", sqrt);
  
  #( 10*CLOCK_PERIOD );
  $finish;  //acaba a simulação
end

//---------------------------------------------------
// Simulate the sequential controller to perform a square root.
task startstates;
input [NBITS-1:0] xin;
 begin
   x = xin;   // Apply operands
  
  @(posedge clock);
  run = 1'b1;       // Assert start
  @(posedge clock );
  run = 1'b0;
  @(posedge clock );  
  while (busy) @(posedge clock);

  @(posedge clock );
  end  
  


endtask


endmodule

Project1/sec_controller_tb.vcd
$date
	Wed Apr 27 20:20:56 2022
$end
$version
	Icarus Verilog
$end
$timescale
	100ps
$end
$scope module sec_controller_tb $end
$var wire 1 ! stop $end
$var wire 1 " start $end
$var wire 8 # sqrt [7:0] $end
$var wire 1 $ busy $end
$var reg 1 % clock $end
$var reg 1 & reset $end
$var reg 1 ' run $end
$var reg 16 ( x [15:0] $end
$scope module psdsqrt_2 $end
$var wire 1 % clock $end
$var wire 1 & reset $end
$var wire 12 ) testsqrt [11:0] $end
$var wire 16 * xin [15:0] $end
$var wire 1 ! stop $end
$var wire 1 " start $end
$var wire 24 + sqtestsqrt [23:0] $end
$var wire 8 , pint [7:0] $end
$var wire 24 - inteiro [23:0] $end
$var wire 1 . greater $end
$var wire 4 / frac [3:0] $end
$var reg 24 0 A_value [23:0] $end
$var reg 12 1 other [11:0] $end
$var reg 8 2 sqrt [7:0] $end
$var reg 12 3 tempsqrt [11:0] $end
$upscope $end
$scope module sec_1 $end
$var wire 1 % clock $end
$var wire 1 & reset $end
$var wire 1 ' run $end
$var reg 1 $ busy $end
$var reg 4 4 conta [3:0] $end
$var reg 1 " start $end
$var reg 2 5 state [1:0] $end
$var reg 1 ! stop $end
$upscope $end
$scope task startstates $end
$var reg 16 6 xin [15:0] $end
$upscope $end
$upscope $end
$enddefinitions $end
#0
$dumpvars
bx 6
bx 5
bx 4
bx 3
bx 2
bx 1
bx 0
bx /
x.
b0 -
bx ,
bx +
b0 *
bx )
b0 (
0'
0&
0%
x$
bx #
x"
x!
$end
#30
1&
#50
0"
0!
0$
b0 4
b0 5
b0xxxxxxxxxxx 1
b0 0
1%
#100
0%
#150
b0xxxxxxxxxx 1
1%
#200
0%
#230
0&
#250
b0xxxxxxxxx 1
1%
#300
0%
#350
b0xxxxxxxx 1
1%
#400
0%
#450
b0xxxxxxx 1
1%
#500
0%
#550
b0xxxxxx 1
1%
#600
0%
#650
b0xxxxx 1
1%
#700
0%
#750
b0xxxx 1
1%
#800
0%
#850
b0xxx 1
1%
#900
0%
#950
b0xx 1
1%
#1000
b110010000000000 -
0%
b1100100 (
b1100100 *
b1100100 6
#1050
1"
b1 5
1$
b0x 1
1'
1%
#1100
0%
#1150
b0 /
b0 ,
0.
b10000000000000000000000 +
b100000000000 )
b100000000000 1
b0 3
b110010000000000 0
0"
0'
1%
#1200
0%
#1250
b100000000000000000000 +
b10000000000 )
b10 5
b1 4
b10000000000 1
1%
#1300
0%
#1350
b1000000000000000000 +
b1000000000 )
b1000000000 1
b10 4
1%
#1400
0%
#1450
b10000000000000000 +
b100000000 )
b11 4
b100000000 1
1%
#1500
0%
#1550
1.
b100000000000000 +
b10000000 )
b10000000 1
b100 4
1%
#1600
0%
#1650
b1000 ,
0.
b1001000000000000 +
b11000000 )
b101 4
b10000000 3
b1000000 1
1%
#1700
0%
#1750
1.
b110010000000000 +
b10100000 )
b100000 1
b110 4
1%
#1800
0%
#1850
b1010 ,
0.
b111100100000000 +
b10110000 )
b111 4
b10100000 3
b10000 1
1%
#1900
0%
#1950
b110111001000000 +
b10101000 )
b1000 1
b1000 4
1%
#2000
0%
#2050
b110100100010000 +
b10100100 )
b1001 4
b100 1
1%
#2100
0%
#2150
b110011010000100 +
b10100010 )
b10 1
b1010 4
1%
#2200
0%
#2250
b110010101000001 +
b10100001 )
b1011 4
b1 1
1%
#2300
0%
#2350
1.
b110010000000000 +
b10100000 )
b0 1
b1100 4
1%
#2400
0%
#2450
b11 5
1!
1%
#2500
0%
#2550
b1010 #
b1010 2
b0 4
b0 5
0$
0!
1%
#2600
0%
#2650
1%
#2700
0%
#2750
b110000000000 -
b1100 (
b1100 *
b1100 6
1%
#2800
0%
#2850
1"
b1 5
1$
1'
1%
#2900
0%
#2950
b0 ,
b10000000000000000000000 +
b100000000000 )
b100000000000 1
b0 3
0.
b110000000000 0
0"
0'
1%
#3000
0%
#3050
b100000000000000000000 +
b10000000000 )
b10 5
b1 4
b10000000000 1
1%
#3100
0%
#3150
b1000000000000000000 +
b1000000000 )
b1000000000 1
b10 4
1%
#3200
0%
#3250
b10000000000000000 +
b100000000 )
b11 4
b100000000 1
1%
#3300
0%
#3350
b100000000000000 +
b10000000 )
b10000000 1
b100 4
1%
#3400
0%
#3450
b1000000000000 +
b1000000 )
b101 4
b1000000 1
1%
#3500
0%
#3550
1.
b10000000000 +
b100000 )
b100000 1
b110 4
1%
#3600
0%
#3650
b10 ,
b100100000000 +
b110000 )
b111 4
b100000 3
b10000 1
1%
#3700
0%
#3750
b11 ,
0.
b110001000000 +
b111000 )
b1000 1
b110000 3
b1000 4
1%
#3800
0%
#3850
1.
b101010010000 +
b110100 )
b1001 4
b100 1
1%
#3900
0%
#3950
b100 /
b101101100100 +
b110110 )
b10 1
b110100 3
b1010 4
1%
#4000
0%
#4050
b110 /
b101111010001 +
b110111 )
b1011 4
b110110 3
b1 1
1%
#4100
0%
#4150
b111 /
b0 1
b110111 3
b1100 4
1%
#4200
0%
#4250
b11 5
1!
1%
#4300
0%
#4350
b11 #
b11 2
b0 4
b0 5
0$
0!
1%
#4400
0%
#4450
1%
#4500
0%
#4550
b110100000000 -
b1101 (
b1101 *
b1101 6
1%
#4600
0%
#4650
1"
b1 5
1$
1'
1%
#4700
0%
#4750
b0 /
b0 ,
0.
b10000000000000000000000 +
b100000000000 )
b100000000000 1
b0 3
b110100000000 0
0"
0'
1%
#4800
0%
#4850
b100000000000000000000 +
b10000000000 )
b10 5
b1 4
b10000000000 1
1%
#4900
0%
#4950
b1000000000000000000 +
b1000000000 )
b1000000000 1
b10 4
1%
#5000
0%
#5050
b10000000000000000 +
b100000000 )
b11 4
b100000000 1
1%
#5100
0%
#5150
b100000000000000 +
b10000000 )
b10000000 1
b100 4
1%
#5200
0%
#5250
b1000000000000 +
b1000000 )
b101 4
b1000000 1
1%
#5300
0%
#5350
1.
b10000000000 +
b100000 )
b100000 1
b110 4
1%
#5400
0%
#5450
b10 ,
b100100000000 +
b110000 )
b111 4
b100000 3
b10000 1
1%
#5500
0%
#5550
b11 ,
b110001000000 +
b111000 )
b1000 1
b110000 3
b1000 4
1%
#5600
0%
#5650
b1000 /
0.
b111000010000 +
b111100 )
b1001 4
b111000 3
b100 1
1%
#5700
0%
#5750
b110100100100 +
b111010 )
b10 1
b1010 4
1%
#5800
0%
#5850
1.
b110010110001 +
b111001 )
b1011 4
b1 1
1%
#5900
0%
#5950
b1001 /
b0 1
b111001 3
b1100 4
1%
#6000
0%
#6050
b11 5
1!
1%
#6100
0%
#6150
b100 #
b100 2
b0 4
b0 5
0$
0!
1%
#6200
0%
#6250
1%
#6300
0%
#6350
b1000010000100000000 -
b10000100001 (
b10000100001 *
b10000100001 6
1%
#6400
0%
#6450
1"
b1 5
1$
1'
1%
#6500
0%
#6550
b0 /
b0 ,
0.
b10000000000000000000000 +
b100000000000 )
b100000000000 1
b0 3
b1000010000100000000 0
0"
0'
1%
#6600
0%
#6650
b100000000000000000000 +
b10000000000 )
b10 5
b1 4
b10000000000 1
1%
#6700
0%
#6750
1.
b1000000000000000000 +
b1000000000 )
b1000000000 1
b10 4
1%
#6800
0%
#6850
b100000 ,
0.
b10010000000000000000 +
b1100000000 )
b11 4
b1000000000 3
b100000000 1
1%
#6900
0%
#6950
b1100100000000000000 +
b1010000000 )
b10000000 1
b100 4
1%
#7000
0%
#7050
b1010001000000000000 +
b1001000000 )
b101 4
b1000000 1
1%
#7100
0%
#7150
b1001000010000000000 +
b1000100000 )
b100000 1
b110 4
1%
#7200
0%
#7250
b1000100000100000000 +
b1000010000 )
b111 4
b10000 1
1%
#7300
0%
#7350
1.
b1000010000001000000 +
b1000001000 )
b1000 1
b1000 4
1%
#7400
0%
#7450
b1000 /
0.
b1000011000010010000 +
b1000001100 )
b1001 4
b1000001000 3
b100 1
1%
#7500
0%
#7550
b1000010100001100100 +
b1000001010 )
b10 1
b1010 4
1%
#7600
0%
#7650
b1000010010001010001 +
b1000001001 )
b1011 4
b1 1
1%
#7700
0%
#7750
1.
b1000010000001000000 +
b1000001000 )
b0 1
b1100 4
1%
#7800
0%
#7850
b11 5
1!
1%
#7900
0%
#7950
b100000 #
b100000 2
b0 4
b0 5
0$
0!
1%
#8000
0%
#8050
1%
#8100
0%
#8150
b100001100110000000000 -
b1000011001100 (
b1000011001100 *
b1000011001100 6
1%
#8200
0%
#8250
1"
b1 5
1$
1'
1%
#8300
0%
#8350
b0 /
b0 ,
0.
b10000000000000000000000 +
b100000000000 )
b100000000000 1
b0 3
b100001100110000000000 0
0"
0'
1%
#8400
0%
#8450
1.
b100000000000000000000 +
b10000000000 )
b10 5
b1 4
b10000000000 1
1%
#8500
0%
#8550
b1000000 ,
0.
b1001000000000000000000 +
b11000000000 )
b1000000000 1
b10000000000 3
b10 4
1%
#8600
0%
#8650
b110010000000000000000 +
b10100000000 )
b11 4
b100000000 1
1%
#8700
0%
#8750
b101000100000000000000 +
b10010000000 )
b10000000 1
b100 4
1%
#8800
0%
#8850
b100100001000000000000 +
b10001000000 )
b101 4
b1000000 1
1%
#8900
0%
#8950
b100010000010000000000 +
b10000100000 )
b100000 1
b110 4
1%
#9000
0%
#9050
1.
b100001000000100000000 +
b10000010000 )
b111 4
b10000 1
1%
#9100
0%
#9150
b1000001 ,
b100001100001001000000 +
b10000011000 )
b1000 1
b10000010000 3
b1000 4
1%
#9200
0%
#9250
b1000 /
0.
b100001110001100010000 +
b10000011100 )
b1001 4
b10000011000 3
b100 1
1%
#9300
0%
#9350
b100001101001010100100 +
b10000011010 )
b10 1
b1010 4
1%
#9400
0%
#9450
1.
b100001100101001110001 +
b10000011001 )
b1011 4
b1 1
1%
#9500
0%
#9550
b1001 /
b0 1
b10000011001 3
b1100 4
1%
#9600
0%
#9650
b11 5
1!
1%
#9700
0%
#9750
b1000010 #
b1000010 2
b0 4
b0 5
0$
0!
1%
